arsenic/__init__.py
arsenic/actions.py
arsenic/browsers.py
arsenic/connection.py
arsenic/constants.py
arsenic/errors.py
arsenic/helpers.py
arsenic/http.py
arsenic/keys.py
arsenic/services.py
arsenic/session.py
arsenic/subprocess.py
arsenic/utils.py
arsenic/webdriver.py
arsenic-19.1.dist-info/LICENSE
arsenic-19.1.dist-info/METADATA
arsenic-19.1.dist-info/WHEEL
arsenic-19.1.dist-info/entry_points.txt
arsenic-19.1.dist-info/top_level.txt
arsenic-19.1.dist-info/RECORD
