Metadata-Version: 2.1
Name: arsenic
Version: 19.1
Summary: Async Webdriver
Home-page: https://github.com/HDE/arsenic
Author: Jonas Obrist
Author-email: ojiidotch@gmail.com
License: APLv2
Project-URL: Documentation, https://arsenic.readthedocs.io/en/latest/
Project-URL: Code, https://github.com/HDE/arsenic
Project-URL: Issue tracker, https://github.com/HDE/arsenic/issues
Platform: UNKNOWN
Classifier: Development Status :: 3 - Alpha
Classifier: License :: OSI Approved :: Apache Software License
Classifier: Programming Language :: Python :: 3 :: Only
Classifier: Programming Language :: Python :: 3.6
Classifier: Programming Language :: Python :: 3.7
Classifier: Programming Language :: Python :: 3.8
Requires-Python: >=3.6
Requires-Dist: attrs (>=17.4.0)
Requires-Dist: structlog
Requires-Dist: aiohttp (>=2)
